bagofconcepts/__init__.py
bagofconcepts/boc.py
bagofconcepts/pagerank.py
bagofconcepts/utils.py
bagofconcepts-0.1.0.dist-info/LICENSE.txt
bagofconcepts-0.1.0.dist-info/METADATA
bagofconcepts-0.1.0.dist-info/WHEEL
bagofconcepts-0.1.0.dist-info/top_level.txt
bagofconcepts-0.1.0.dist-info/RECORD
